waldur_auth_openid/__init__.py
waldur_auth_openid/apps.py
waldur_auth_openid/auth.py
waldur_auth_openid/extension.py
waldur_auth_openid/log.py
waldur_auth_openid/urls.py
waldur_auth_openid/views.py
waldur_auth_openid/migrations/__init__.py
waldur_auth_openid-0.8.5.dist-info/DESCRIPTION.rst
waldur_auth_openid-0.8.5.dist-info/METADATA
waldur_auth_openid-0.8.5.dist-info/RECORD
waldur_auth_openid-0.8.5.dist-info/WHEEL
waldur_auth_openid-0.8.5.dist-info/entry_points.txt
waldur_auth_openid-0.8.5.dist-info/metadata.json
waldur_auth_openid-0.8.5.dist-info/top_level.txt
