Metadata-Version: 2.0
Name: waldur-auth-openid
Version: 0.8.5
Summary: Waldur plugin bringing OpenID-based authentication support.
Home-page: http://waldur.com
Author: OpenNode Team
Author-email: info@opennodecloud.com
License: MIT
Platform: UNKNOWN
Classifier: Framework :: Django
Classifier: Intended Audience :: Developers
Classifier: Intended Audience :: System Administrators
Classifier: Operating System :: OS Independent
Classifier: License :: OSI Approved :: MIT License
Requires-Dist: django-openid-auth (>=0.14)
Requires-Dist: nodeconductor (>0.138.0)
Provides-Extra: dev
Requires-Dist: Sphinx (==1.2.2); extra == 'dev'
